{"chunk_definitions":[{"row":26,"row_count":1,"visible":true,"expansion_state":0,"options":{"engine":"r","label":"setup","include":false},"document_id":"6A5BD52A","chunk_id":"csetup_chunk","chunk_label":"setup"},{"row":34,"row_count":1,"visible":true,"expansion_state":0,"options":{"engine":"r","echo":false,"out.width":"60%","label":"unnamed-chunk-1"},"document_id":"6A5BD52A","chunk_id":"cfrhz0pnisg3i","chunk_label":"unnamed-chunk-1"},{"row":40,"row_count":1,"visible":true,"expansion_state":0,"options":{"engine":"r","echo":false,"out.width":"60%","label":"unnamed-chunk-2"},"document_id":"6A5BD52A","chunk_id":"c7rglh66gay6g","chunk_label":"unnamed-chunk-2"},{"row":52,"row_count":1,"visible":true,"expansion_state":0,"options":{"engine":"r","label":"unnamed-chunk-3"},"document_id":"6A5BD52A","chunk_id":"cjr2k3s8esadm","chunk_label":"unnamed-chunk-3"},{"row":69,"row_count":1,"visible":true,"expansion_state":0,"options":{"engine":"r","label":"unnamed-chunk-4"},"document_id":"6A5BD52A","chunk_id":"cfd89rsxzz1kc","chunk_label":"unnamed-chunk-4"},{"row":79,"row_count":1,"visible":true,"expansion_state":0,"options":{"engine":"r","label":"unnamed-chunk-5"},"document_id":"6A5BD52A","chunk_id":"c5pbwl1ydlbjv","chunk_label":"unnamed-chunk-5"},{"row":97,"row_count":1,"visible":true,"expansion_state":0,"options":{"engine":"r","label":"unnamed-chunk-19"},"document_id":"6A5BD52A","chunk_id":"csel0uuqu4w3x","chunk_label":"unnamed-chunk-6"},{"row":107,"row_count":1,"visible":true,"expansion_state":0,"options":{"engine":"r","label":"unnamed-chunk-17"},"document_id":"6A5BD52A","chunk_id":"ceg7klxbschpz","chunk_label":"unnamed-chunk-7"},{"row":115,"row_count":1,"visible":true,"expansion_state":0,"options":{"engine":"r","label":"unnamed-chunk-6"},"document_id":"6A5BD52A","chunk_id":"c5ndko0i5vipu","chunk_label":"unnamed-chunk-8"},{"row":145,"row_count":1,"visible":true,"expansion_state":0,"options":{"engine":"r","label":"unnamed-chunk-7"},"document_id":"6A5BD52A","chunk_id":"c345yw3ii9dzp","chunk_label":"unnamed-chunk-9"},{"row":153,"row_count":1,"visible":true,"expansion_state":0,"options":{"engine":"r","label":"unnamed-chunk-8"},"document_id":"6A5BD52A","chunk_id":"cts5nn1nz3ufv","chunk_label":"unnamed-chunk-10"},{"row":162,"row_count":1,"visible":true,"expansion_state":0,"options":{"engine":"r","label":"unnamed-chunk-9"},"document_id":"6A5BD52A","chunk_id":"cdurofvtrvjn4","chunk_label":"unnamed-chunk-11"},{"row":178,"row_count":1,"visible":true,"expansion_state":0,"options":{"engine":"r","label":"unnamed-chunk-10"},"document_id":"6A5BD52A","chunk_id":"cqca4fajk7d23","chunk_label":"unnamed-chunk-12"},{"row":186,"row_count":1,"visible":true,"expansion_state":0,"options":{"engine":"r","label":"unnamed-chunk-11"},"document_id":"6A5BD52A","chunk_id":"csv7qrbg2wmqq","chunk_label":"unnamed-chunk-13"},{"row":210,"row_count":1,"visible":true,"expansion_state":0,"options":{"engine":"r","label":"unnamed-chunk-37"},"document_id":"6A5BD52A","chunk_id":"cl59gwe1m1p7b","chunk_label":"unnamed-chunk-14"},{"row":226,"row_count":1,"visible":true,"expansion_state":0,"options":{"engine":"r","label":"unnamed-chunk-44"},"document_id":"6A5BD52A","chunk_id":"cek1o320w9iny","chunk_label":"unnamed-chunk-15"},{"row":235,"row_count":1,"visible":true,"expansion_state":0,"options":{"engine":"r","label":"unnamed-chunk-45"},"document_id":"6A5BD52A","chunk_id":"caeoni0u1oipx","chunk_label":"unnamed-chunk-16"},{"row":260,"row_count":1,"visible":true,"expansion_state":0,"options":{"engine":"r","label":"unnamed-chunk-46"},"document_id":"6A5BD52A","chunk_id":"cgg4osvxen8pc","chunk_label":"unnamed-chunk-17"},{"row":298,"row_count":1,"visible":true,"expansion_state":0,"options":{"engine":"r","label":"unnamed-chunk-22"},"document_id":"6A5BD52A","chunk_id":"czon3an7khkw0","chunk_label":"unnamed-chunk-20"},{"row":306,"row_count":1,"visible":true,"expansion_state":0,"options":{"engine":"r","label":"unnamed-chunk-24"},"document_id":"6A5BD52A","chunk_id":"cbq5w3714k70c","chunk_label":"unnamed-chunk-21"},{"row":326,"row_count":1,"visible":true,"expansion_state":0,"options":{"engine":"r","label":"unnamed-chunk-49"},"document_id":"6A5BD52A","chunk_id":"cdxy03s7ii3bt","chunk_label":"unnamed-chunk-22"},{"row":385,"row_count":1,"visible":true,"expansion_state":0,"options":{"engine":"r","label":"unnamed-chunk-58"},"document_id":"6A5BD52A","chunk_id":"cba6n9gjfc6q6","chunk_label":"unnamed-chunk-24"},{"row":396,"row_count":1,"visible":true,"expansion_state":0,"options":{"engine":"r","label":"unnamed-chunk-59"},"document_id":"6A5BD52A","chunk_id":"cq19omyrad0bj","chunk_label":"unnamed-chunk-25"}],"doc_write_time":1665123629,"chunk_rendered_width":661}